nmodl_preprocessor/__main__.py
nmodl_preprocessor/cpp_keywords.py
nmodl_preprocessor/nmodl_to_python.py
nmodl_preprocessor/optimize_nmodl.py
nmodl_preprocessor/rw_patterns.py
nmodl_preprocessor/utils.py
nmodl_preprocessor-1.0.8.dist-info/LICENSE.txt
nmodl_preprocessor-1.0.8.dist-info/METADATA
nmodl_preprocessor-1.0.8.dist-info/WHEEL
nmodl_preprocessor-1.0.8.dist-info/entry_points.txt
nmodl_preprocessor-1.0.8.dist-info/top_level.txt
nmodl_preprocessor-1.0.8.dist-info/RECORD
