Metadata-Version: 2.1
Name: nmodl-preprocessor
Version: 1.0.8
Summary: Optimize NMODL files for the NEURON simulator
Author-email: David McDougall <dam1784@rit.edu>
License: MIT
Project-URL: Homepage, https://github.com/ctrl-z-9000-times/nmodl_preprocessor
Keywords: nmodl,neuron
Classifier: Programming Language :: Python :: 3
Classifier: Environment :: Console
Classifier: Intended Audience :: Science/Research
Classifier: Topic :: Scientific/Engineering
Classifier: Development Status :: 5 - Production/Stable
Classifier: Natural Language :: English
Classifier: License :: OSI Approved :: MIT License
Classifier: Operating System :: OS Independent
Requires-Python: >=3.8
License-File: LICENSE.txt
Requires-Dist: nmodl
